README.md
setup.cfg
setup.py
django_splitio/__init__.py
django_splitio/factories.py
django_splitio/version.py
django_splitio.egg-info/PKG-INFO
django_splitio.egg-info/SOURCES.txt
django_splitio.egg-info/dependency_links.txt
django_splitio.egg-info/requires.txt
django_splitio.egg-info/top_level.txt