Metadata-Version: 2.1
Name: django-splitio
Version: 2.4.0
Summary: Split.io Django Application
Home-page: https://github.com/splitio/django-splitio
Author: Patricio Echague, Sebastian Arrubia
Author-email: pato@split.io, sebastian@split.io
License: Apache License 2.0
Platform: UNKNOWN
Classifier: Development Status :: 2 - Pre-Alpha
Classifier: Environment :: Console
Classifier: Intended Audience :: Developers
Classifier: Programming Language :: Python
Classifier: Programming Language :: Python :: 2
Classifier: Programming Language :: Python :: 3
Classifier: Topic :: Software Development :: Libraries
Provides-Extra: redis
Provides-Extra: uwsgi
